README.rst
setup.py
zabbix_api_client/__init__.py
zabbix_api_client/client.py
zabbix_api_client/maintenance.py
zabbix_api_client.egg-info/PKG-INFO
zabbix_api_client.egg-info/SOURCES.txt
zabbix_api_client.egg-info/dependency_links.txt
zabbix_api_client.egg-info/requires.txt
zabbix_api_client.egg-info/top_level.txt