Metadata-Version: 1.0
Name: zabbix-api-client
Version: 0.0.1
Summary: Zabbix API client library
Home-page: https://github.com/osamunmun/zabbix-api-client
Author: Osamu Takayasu
Author-email: osamu.takayasu@gmail.com
License: MIT
Platform: UNKNOWN
